sf2easy/__init__.py
sf2easy/sf2easy.py
salesforce2easy-0.1.dist-info/METADATA
salesforce2easy-0.1.dist-info/WHEEL
salesforce2easy-0.1.dist-info/top_level.txt
salesforce2easy-0.1.dist-info/RECORD
