Metadata-Version: 2.1
Name: salesforce2easy
Version: 0.1
Summary: A Salesforce integration helper library
Home-page: https://github.com/Antonio-Moura-Coutinho/SalesforceImproveLibrary
Author-email: tonitrigueiros@gmail.com
Classifier: Programming Language :: Python :: 3
Classifier: License :: OSI Approved :: MIT License
Classifier: Operating System :: OS Independent
Requires-Python: >=3.10
Requires-Dist: simple-salesforce
Requires-Dist: pandas
